telemetry_sh/__init__.py
telemetry_sh/telemetry.py
telemetry_sh/telemetry_async.py
telemetry_sh-1.0.9.dist-info/LICENSE
telemetry_sh-1.0.9.dist-info/METADATA
telemetry_sh-1.0.9.dist-info/WHEEL
telemetry_sh-1.0.9.dist-info/top_level.txt
telemetry_sh-1.0.9.dist-info/RECORD
